README.md
catalog.json
config.json
setup.py
state.json
tap_twitter/__init__.py
tap_twitter.egg-info/PKG-INFO
tap_twitter.egg-info/SOURCES.txt
tap_twitter.egg-info/dependency_links.txt
tap_twitter.egg-info/entry_points.txt
tap_twitter.egg-info/requires.txt
tap_twitter.egg-info/top_level.txt
tap_twitter/schemas/blocks.json
tap_twitter/schemas/favorites.json
tap_twitter/schemas/followers.json
tap_twitter/schemas/friends.json
tap_twitter/schemas/home_timeline.json
tap_twitter/schemas/lists.json
tap_twitter/schemas/memberships.json
tap_twitter/schemas/mentions.json
tap_twitter/schemas/replies.json
tap_twitter/schemas/retweets_of_me.json
tap_twitter/schemas/subscriptions.json
tap_twitter/schemas/user_retweets.json
tap_twitter/schemas/user_timeline.json