Metadata-Version: 1.1
Name: tap-twitter
Version: 2.0.2
Summary: Singer.io tap for fetching data from Twitter API
Home-page: http://singer.io
Author: Bernard Tai
Author-email: bernietai@gmail.com
License: UNKNOWN
Platform: UNKNOWN
Classifier: Programming Language :: Python
